LICENSE
sqlitetools/__init__.py
sqlitetools/py.typed
sqlitetools-0.0.5.dist-info/LICENSE
sqlitetools-0.0.5.dist-info/METADATA
sqlitetools-0.0.5.dist-info/WHEEL
sqlitetools-0.0.5.dist-info/RECORD
